MicroGCFusionAPI/ModuleMethods.json
MicroGCFusionAPI/__init__.py
MicroGCFusionAPI/fusion.py
microgcfusionapi-0.0.8.dist-info/licenses/LICENSE
microgcfusionapi-0.0.8.dist-info/METADATA
microgcfusionapi-0.0.8.dist-info/WHEEL
microgcfusionapi-0.0.8.dist-info/top_level.txt
microgcfusionapi-0.0.8.dist-info/RECORD
