Metadata-Version: 2.4
Name: MicroGCFusionAPI
Version: 0.0.8
Summary: Micro GC Fusion API
License: MIT License
Project-URL: Homepage, https://bitbucket.org/inficon-global/microgcfusionapi/src/main/
Keywords: chromatography,GC,inficon,gas chromatography,micro,Fusion,MicroGC,API,MicroGCFusionAPI,Micro GC Fusion
Classifier: License :: OSI Approved :: MIT License
Classifier: Intended Audience :: Developers
Classifier: Development Status :: 3 - Alpha
Classifier: Intended Audience :: End Users/Desktop
Classifier: Intended Audience :: Science/Research
Classifier: Programming Language :: Python :: 3
Classifier: Topic :: Scientific/Engineering
Requires-Python: >=3.8
License-File: LICENSE
Requires-Dist: requests
Requires-Dist: importlib-metadata; python_version >= "3.8"
Requires-Dist: numpy
Dynamic: license-file
